flx/__init__.py
flx/cli.py
xneo-0.1.0.dist-info/licenses/LICENSE
xneo-0.1.0.dist-info/METADATA
xneo-0.1.0.dist-info/WHEEL
xneo-0.1.0.dist-info/entry_points.txt
xneo-0.1.0.dist-info/top_level.txt
xneo-0.1.0.dist-info/RECORD
