Metadata-Version: 2.4
Name: xneo
Version: 0.1.0
Summary: A lightweight CLI tool for executing and serving AI flows
Home-page: https://github.com/neopilot-ai/xneo
Author: NeoAI
Author-email: NeoAI <info@khulnasoft.com>
License: MIT
Project-URL: Homepage, https://github.com/neopilot-ai/xneo
Classifier: Development Status :: 3 - Alpha
Classifier: Intended Audience :: Developers
Classifier: Programming Language :: Python :: 3
Classifier: License :: OSI Approved :: MIT License
Classifier: Operating System :: OS Independent
Requires-Python: >=3.6
License-File: LICENSE
Dynamic: author
Dynamic: home-page
Dynamic: license-file
Dynamic: requires-python
